{"4": 1, "the": 88, "same": 1, "subject": 1, "continued": 1, "concerning": 1, "dangers": 2, "from": 9, "foreign": 4, "force": 2, "and": 91, "influence": 1, "for": 13, "independent": 6, "journal": 1, "wednesday": 1, "november": 1, "7": 1, "1787": 1, "jay": 1, "to": 51, "people": 8, "of": 72, "state": 6, "new": 1, "york": 1, "my": 1, "last": 1, "paper": 1, "assigned": 1, "several": 2, "reasons": 2, "why": 1, "safety": 5, "would": 17, "be": 26, "best": 2, "secured": 1, "by": 14, "union": 4, "against": 6, "danger": 2, "it": 28, "may": 10, "exposed": 1, "just": 3, "causes": 4, "war": 8, "given": 3, "other": 11, "nations": 9, "those": 4, "show": 1, "that": 17, "such": 9, "not": 17, "only": 4, "more": 13, "rarely": 1, "but": 10, "also": 2, "easily": 2, "accommodated": 1, "a": 16, "national": 7, "government": 16, "than": 9, "either": 4, "governments": 4, "or": 24, "proposed": 1, "little": 1, "confederacies": 4, "america": 5, "depends": 2, "on": 11, "their": 19, "forbearing": 1, "give": 3, "placing": 1, "continuing": 1, "themselves": 3, "in": 24, "situation": 6, "as": 20, "invite": 1, "hostility": 1, "insult": 1, "need": 1, "observed": 1, "there": 3, "are": 11, "pretended": 1, "well": 4, "is": 10, "too": 2, "true": 1, "however": 1, "disgraceful": 1, "human": 1, "nature": 1, "general": 2, "will": 15, "make": 4, "whenever": 2, "they": 17, "have": 9, "prospect": 1, "getting": 1, "anything": 1, "nay": 1, "absolute": 2, "monarchs": 1, "often": 4, "when": 4, "get": 1, "nothing": 1, "purposes": 1, "objects": 1, "merely": 1, "personal": 2, "thirst": 1, "military": 1, "glory": 1, "revenge": 1, "affronts": 1, "ambition": 1, "private": 1, "compacts": 1, "aggrandize": 1, "support": 1, "particular": 3, "families": 1, "partisans": 1, "these": 6, "variety": 1, "motives": 1, "which": 10, "affect": 2, "mind": 1, "sovereign": 1, "lead": 1, "him": 1, "engage": 2, "wars": 1, "sanctified": 1, "justice": 1, "voice": 1, "interests": 3, "his": 2, "inducements": 3, "prevalent": 1, "monarchies": 1, "deserve": 1, "our": 18, "attention": 2, "others": 3, "kings": 1, "some": 2, "them": 12, "examination": 1, "found": 2, "grow": 1, "out": 2, "relative": 2, "circumstances": 3, "with": 12, "france": 2, "britain": 7, "we": 10, "rivals": 2, "fisheries": 1, "can": 11, "supply": 2, "markets": 1, "cheaper": 1, "notwithstanding": 1, "any": 5, "efforts": 1, "prevent": 1, "bounties": 1, "own": 4, "duties": 1, "fish": 1, "most": 1, "european": 1, "navigation": 6, "carrying": 2, "trade": 4, "shall": 6, "deceive": 1, "ourselves": 2, "if": 13, "suppose": 2, "rejoice": 1, "see": 4, "flourish": 1, "increase": 1, "without": 2, "degree": 1, "diminishing": 1, "theirs": 1, "interest": 3, "policy": 3, "restrain": 1, "promote": 1, "china": 1, "india": 1, "interfere": 1, "one": 13, "nation": 1, "inasmuch": 1, "enables": 1, "us": 8, "partake": 1, "advantages": 2, "had": 3, "manner": 1, "monopolized": 1, "thereby": 2, "commodities": 1, "used": 1, "purchase": 1, "extension": 1, "commerce": 1, "vessels": 1, "pleasure": 1, "who": 3, "possess": 1, "territories": 2, "near": 1, "this": 1, "continent": 1, "because": 1, "cheapness": 1, "excellence": 1, "productions": 1, "added": 1, "circumstance": 1, "vicinity": 1, "enterprise": 1, "address": 1, "merchants": 1, "navigators": 1, "greater": 1, "share": 1, "afford": 1, "consists": 2, "wishes": 1, "respective": 2, "sovereigns": 1, "spain": 2, "thinks": 1, "convenient": 2, "shut": 1, "mississippi": 1, "side": 1, "excludes": 1, "saint": 1, "lawrence": 1, "nor": 1, "permit": 1, "waters": 1, "between": 2, "become": 2, "means": 2, "mutual": 1, "intercourse": 1, "traffic": 1, "like": 1, "considerations": 1, "might": 2, "consistent": 1, "prudence": 1, "amplified": 1, "detailed": 1, "easy": 2, "jealousies": 1, "uneasinesses": 1, "gradually": 1, "slide": 1, "into": 10, "minds": 1, "cabinets": 1, "expect": 1, "should": 1, "regard": 2, "advancement": 1, "power": 2, "consequence": 1, "land": 1, "sea": 1, "an": 3, "eye": 1, "indifference": 1, "composure": 1, "aware": 1, "arise": 1, "so": 5, "obvious": 1, "at": 2, "present": 2, "find": 2, "fit": 1, "time": 2, "opportunity": 1, "operation": 1, "pretenses": 1, "color": 1, "justify": 1, "wanting": 1, "wisely": 1, "therefore": 1, "do": 2, "consider": 1, "good": 2, "necessary": 1, "put": 1, "keep": 1, "instead": 1, "inviting": 1, "tend": 1, "repress": 1, "discourage": 1, "possible": 1, "defense": 3, "necessarily": 1, "arms": 1, "resources": 4, "country": 1, "whole": 6, "provided": 1, "many": 1, "let": 2, "inquire": 1, "whether": 2, "object": 1, "question": 1, "competent": 1, "number": 2, "whatever": 3, "collect": 1, "avail": 1, "itself": 1, "talents": 1, "experience": 2, "ablest": 1, "men": 2, "part": 2, "move": 1, "uniform": 1, "principles": 1, "harmonize": 1, "assimilate": 1, "protect": 1, "parts": 3, "members": 1, "extend": 1, "benefit": 1, "its": 9, "foresight": 1, "precautions": 1, "each": 4, "formation": 1, "treaties": 1, "connected": 1, "apply": 2, "expeditiously": 1, "separate": 1, "possibly": 1, "want": 1, "concert": 1, "unity": 1, "system": 1, "place": 1, "militia": 6, "under": 4, "plan": 1, "discipline": 1, "putting": 1, "officers": 1, "proper": 1, "line": 1, "subordination": 1, "chief": 1, "magistrate": 1, "were": 1, "consolidate": 1, "corps": 1, "render": 1, "efficient": 2, "divided": 2, "thirteen": 2, "three": 5, "four": 5, "distinct": 1, "companies": 1, "what": 5, "english": 1, "obeyed": 3, "england": 2, "scotch": 1, "scotland": 2, "welsh": 1, "wales": 2, "invasion": 1, "agreed": 1, "all": 4, "able": 1, "forces": 1, "operate": 1, "enemy": 1, "effectually": 1, "single": 1, "great": 2, "heard": 1, "much": 2, "fleets": 4, "come": 1, "wise": 2, "regulated": 2, "nursery": 1, "seamenif": 1, "called": 1, "forth": 1, "materials": 1, "forming": 1, "prowess": 1, "thunder": 1, "never": 2, "been": 2, "celebrated": 1, "fleetlet": 4, "ireland": 1, "constituent": 1, "british": 1, "empire": 1, "perceive": 1, "how": 4, "soon": 2, "dwindle": 1, "comparative": 1, "insignificance": 1, "facts": 1, "case": 2, "leave": 1, "you": 1, "please": 1, "governmentswhat": 1, "armies": 2, "could": 2, "raise": 1, "paywhat": 1, "ever": 1, "hope": 1, "was": 1, "attacked": 1, "fly": 1, "succor": 1, "spend": 1, "blood": 1, "money": 2, "no": 1, "being": 1, "flattered": 1, "neutrality": 1, "specious": 1, "promises": 1, "seduced": 1, "fondness": 1, "peace": 2, "decline": 1, "hazarding": 1, "tranquillity": 1, "sake": 1, "neighbors": 1, "whom": 1, "perhaps": 2, "jealous": 1, "whose": 1, "importance": 1, "content": 1, "diminished": 1, "although": 1, "conduct": 1, "nevertheless": 1, "natural": 1, "history": 1, "states": 1, "greece": 1, "countries": 1, "abounds": 1, "instances": 1, "improbable": 1, "has": 1, "happened": 1, "similar": 1, "happen": 1, "again": 1, "admit": 1, "willing": 1, "help": 1, "invaded": 1, "confederacy": 1, "proportion": 1, "aids": 1, "afforded": 1, "command": 1, "allied": 1, "he": 1, "receive": 1, "orders": 1, "settle": 1, "terms": 1, "disputes": 1, "umpire": 1, "decide": 1, "compel": 1, "acquiescence": 1, "various": 1, "difficulties": 1, "inconveniences": 1, "inseparable": 1, "whereas": 1, "watching": 1, "over": 1, "common": 1, "combining": 1, "directing": 1, "powers": 1, "free": 2, "embarrassments": 1, "conduce": 1, "far": 1, "firmly": 1, "united": 2, "split": 2, "certain": 1, "know": 1, "view": 1, "exactly": 1, "act": 1, "toward": 1, "accordingly": 1, "administered": 1, "prudently": 1, "properly": 1, "organized": 1, "disciplined": 1, "finances": 1, "discreetly": 1, "managed": 1, "credit": 1, "reestablished": 1, "contented": 1, "disposed": 1, "cultivate": 1, "friendship": 1, "provoke": 1, "resentment": 1, "hand": 1, "destitute": 1, "effectual": 1, "doing": 1, "right": 1, "wrong": 1, "rulers": 1, "seem": 1, "probably": 1, "discordant": 1, "republics": 1, "inclining": 1, "another": 1, "third": 1, "played": 1, "off": 1, "poor": 1, "pitiful": 1, "figure": 1, "eyes": 1, "liable": 1, "she": 1, "contempt": 1, "outrage": 1, "dearbought": 1, "proclaim": 1, "family": 1, "divide": 1, "fails": 1, "publius": 1}